mlx90640_mcp2221/__init__.py
mlx90640_mcp2221/cli.py
mlx90640_mcp2221/mcp2221.py
mlx90640_mcp2221/libs/aarch64/libhidapi-hidraw.so
mlx90640_mcp2221/libs/aarch64/libmlx90640_driver_mcp2221.so
mlx90640_mcp2221/libs/aarch64/libudev.so
mlx90640_mcp2221/libs/armv7l/libhidapi-hidraw.so
mlx90640_mcp2221/libs/armv7l/libmlx90640_driver_mcp2221.so
mlx90640_mcp2221/libs/armv7l/libudev.so
mlx90640_mcp2221/libs/windows/hidapi.dll
mlx90640_mcp2221/libs/windows/mlx90640_driver_mcp2221.dll
mlx90640_mcp2221/libs/x86_64/libmlx90640_driver_mcp2221.so
mlx90640_driver_mcp2221-1.1.0.dist-info/LICENSE
mlx90640_driver_mcp2221-1.1.0.dist-info/METADATA
mlx90640_driver_mcp2221-1.1.0.dist-info/NOTICE
mlx90640_driver_mcp2221-1.1.0.dist-info/WHEEL
mlx90640_driver_mcp2221-1.1.0.dist-info/entry_points.txt
mlx90640_driver_mcp2221-1.1.0.dist-info/top_level.txt
mlx90640_driver_mcp2221-1.1.0.dist-info/RECORD
