Metadata-Version: 2.1
Name: mlx90640-driver-mcp2221
Version: 1.1.0
Summary: I2C for MLX90640 using the EVB90640-41 on (windows 10, linux pc, raspberry pi, jetson nano, beagle bone, ...)
Home-page: https://github.com/melexis-fir/mlx90640-driver-mcp2221-py
Author: Karel Vanroye
Author-email: kva@melexis.com
Maintainer: melexis-fir
License: Apache License, Version 2.0
Project-URL: Documentation, https://melexis-fir.github.io/mlx90640-driver-mcp2221-py/
Project-URL: Source Code, https://github.com/melexis-fir/mlx90640-driver-mcp2221-py
Project-URL: Issue Tracker, https://github.com/melexis-fir/mlx90640-driver-mcp2221-py/issues
Platform: UNKNOWN
Classifier: Development Status :: 5 - Production/Stable
Classifier: Intended Audience :: Developers
Classifier: License :: OSI Approved :: Apache Software License
Classifier: Operating System :: Microsoft :: Windows
Classifier: Operating System :: POSIX
Classifier: Programming Language :: Python :: 3.6
Classifier: Topic :: Utilities
Requires-Python: >=3.6
Requires-Dist: mlx90640-driver (>=1.1.2)
